{"cameraMode":{"drawMode":0,"name":"Shaded","section":"Shading Mode"},"sceneLighting":false,"audioPlay":false,"sceneViewState":{"m_AlwaysRefresh":false,"showFog":true,"showSkybox":false,"showFlares":true,"showImageEffects":true,"showParticleSystems":true,"showVisualEffectGraphs":true,"m_FxEnabled":true},"in2DMode":false,"pivot":{"x":7.685271739959717,"y":-22.46433448791504,"z":131.9329833984375},"rotation":{"x":-0.42037272453308108,"y":-0.565464198589325,"z":0.4115181565284729,"w":-0.5783358812332153},"size":45.27692413330078,"orthographic":false}